LICENSE.txt
MANIFEST.in
setup.py
proji/__init__.py
proji/projectdb_api.py
proji/projectdb_models.py
proji/proji.py
proji.egg-info/PKG-INFO
proji.egg-info/SOURCES.txt
proji.egg-info/dependency_links.txt
proji.egg-info/entry_points.txt
proji.egg-info/requires.txt
proji.egg-info/top_level.txt