Metadata-Version: 1.0
Name: proji
Version: 0.3
Summary: Project management helper
Home-page: UNKNOWN
Author: Markus Binsteiner
Author-email: makkus@gmail.com
License: UNKNOWN
Platform: UNKNOWN
